setup.py
exec_pypeline/__init__.py
exec_pypeline/action.py
exec_pypeline/pipeline.py
exec_pypeline/version.py
exec_pypeline.egg-info/PKG-INFO
exec_pypeline.egg-info/SOURCES.txt
exec_pypeline.egg-info/dependency_links.txt
exec_pypeline.egg-info/entry_points.txt
exec_pypeline.egg-info/requires.txt
exec_pypeline.egg-info/top_level.txt
tests/__init__.py
tests/pass_action.py
tests/test_action.py
tests/test_pipeline.py
tests/test_version.py