Metadata-Version: 1.1
Name: exec-pypeline
Version: 0.4.2
Summary: an incredible python package
Home-page: https://github.com/rfloriano/pypeline
Author: Rafael Floriano da Silva
Author-email: rflorianobr@gmail.com
License: MIT
Platform: UNKNOWN
Classifier: Development Status :: 4 - Beta
Classifier: Intended Audience :: Developers
Classifier: License :: OSI Approved :: MIT License
Classifier: Natural Language :: English
Classifier: Operating System :: Unix
Classifier: Programming Language :: Python :: 2.7
Classifier: Programming Language :: Python :: 3.4
Classifier: Programming Language :: Python :: Implementation :: PyPy
Classifier: Operating System :: OS Independent
